collect_offline_app/__init__.py
collect_offline_app/admin.py
collect_offline_app/apps.py
collect_offline_app/models.py
collect_offline_app/tests.py
collect_offline_app/views.py
collect_offline_app/migrations/__init__.py
django_collect_offline/__init__.py
django_collect_offline/admin.py
django_collect_offline/admin_site.py
django_collect_offline/apps.py
django_collect_offline/choices.py
django_collect_offline/constants.py
django_collect_offline/navbars.py
django_collect_offline/offline_model.py
django_collect_offline/offline_view_mixin.py
django_collect_offline/parsers.py
django_collect_offline/serializers.py
django_collect_offline/site_offline_models.py
django_collect_offline/urls.py
django_collect_offline/management/__init__.py
django_collect_offline/management/commands/__init__.py
django_collect_offline/management/commands/deserialize.py
django_collect_offline/migrations/0001_initial.py
django_collect_offline/migrations/0002_auto_20190114_0250.py
django_collect_offline/migrations/0003_auto_20190305_0123.py
django_collect_offline/migrations/__init__.py
django_collect_offline/model_mixins/__init__.py
django_collect_offline/model_mixins/host_model_mixin.py
django_collect_offline/model_mixins/transaction_model_mixin.py
django_collect_offline/models/__init__.py
django_collect_offline/models/client.py
django_collect_offline/models/incoming_transaction.py
django_collect_offline/models/outgoing_transaction.py
django_collect_offline/models/server.py
django_collect_offline/models/signals.py
django_collect_offline/rest/__init__.py
django_collect_offline/rest/binary_field.py
django_collect_offline/rest/serializers.py
django_collect_offline/static/django_offline/js/edc_sync.js
django_collect_offline/static/django_offline/js/file_transfer.js
django_collect_offline/static/django_offline/js/middleman.js
django_collect_offline/templates/django_collect_offline/client.html
django_collect_offline/templates/django_collect_offline/home.html
django_collect_offline-0.2.49.dist-info/AUTHORS
django_collect_offline-0.2.49.dist-info/LICENSE
django_collect_offline-0.2.49.dist-info/METADATA
django_collect_offline-0.2.49.dist-info/WHEEL
django_collect_offline-0.2.49.dist-info/top_level.txt
django_collect_offline-0.2.49.dist-info/RECORD
