Metadata-Version: 2.1
Name: django-collect-offline
Version: 0.2.49
Summary: Collect data offline and push to the server later.
Home-page: https://github.com/erikvw/django-collect-offline
Author: Erik van Widenfelt
Author-email: ew2789@gmail.com
License: GPL license, see LICENSE
Keywords: django data synchronization offline-use
Platform: UNKNOWN
Classifier: Environment :: Web Environment
Classifier: Framework :: Django
Classifier: Intended Audience :: Developers
Classifier: Intended Audience :: Science/Research
Classifier: License :: OSI Approved :: GNU General Public License v3 (GPLv3)
Classifier: Operating System :: OS Independent
Classifier: Programming Language :: Python :: 3.7
Classifier: Topic :: Internet :: WWW/HTTP
Classifier: Topic :: Internet :: WWW/HTTP :: Dynamic Content
Requires-Python: >=3.7
Requires-Dist: django-collect-offline-files
Requires-Dist: django-cors-headers
Requires-Dist: django-crypto-fields
Requires-Dist: django-js-reverse
Requires-Dist: djangorestframework
Requires-Dist: edc-sites
Requires-Dist: edc-device
Requires-Dist: edc-protocol
Requires-Dist: requests
